unified_api_log/__init__.py
unified_api_log/gunicorn.py
unified_api_log/log.py
Unified_FastAPI_Gunicorn_Log-0.4.2.dist-info/LICENSE
Unified_FastAPI_Gunicorn_Log-0.4.2.dist-info/METADATA
Unified_FastAPI_Gunicorn_Log-0.4.2.dist-info/WHEEL
Unified_FastAPI_Gunicorn_Log-0.4.2.dist-info/top_level.txt
Unified_FastAPI_Gunicorn_Log-0.4.2.dist-info/RECORD
