Metadata-Version: 2.1
Name: Unified-FastAPI-Gunicorn-Log
Version: 0.4.2
Summary: Unified FastAPI, Uvicorn, and Gunicorn logger by Logguru
Home-page: https://github.com/pahntanapat/Unified-FastAPI-Gunicorn-Log
Author: Tanapat Kahabodeekanokkul
Author-email: contact@sati.co.th
License: UNKNOWN
Project-URL: Bug Tracker, https://github.com/pahntanapat/Unified-FastAPI-Gunicorn-Log/issues
Platform: UNKNOWN
Classifier: Programming Language :: Python :: 3
Classifier: License :: OSI Approved :: MIT License
Classifier: Operating System :: OS Independent
Requires-Python: >=3.6
License-File: LICENSE
Requires-Dist: loguru
Requires-Dist: gunicorn
Requires-Dist: uvicorn
